caluxPy_fi/Convexity.py
caluxPy_fi/ExternalImport.py
caluxPy_fi/ExternalImport2.py
caluxPy_fi/FixedIncome.py
caluxPy_fi/Multiple.py
caluxPy_fi/Portfolio.py
caluxPy_fi/Support.py
caluxPy_fi/__init__.py
caluxpy_fi-0.1.99.dist-info/licenses/LICENSE.txt
caluxpy_fi-0.1.99.dist-info/METADATA
caluxpy_fi-0.1.99.dist-info/WHEEL
caluxpy_fi-0.1.99.dist-info/top_level.txt
caluxpy_fi-0.1.99.dist-info/RECORD
