Metadata-Version: 2.4
Name: caluxPy_fi
Version: 0.1.99
Summary: Fixed Income Valuation and Analysis
Author-email: Luis Manuel Tavarez Valenzuela <luima2494@gmail.com>
Maintainer-email: Luis Manuel Tavarez Valenzuela <luima2494@gmail.com>
License-Expression: MIT
Classifier: Programming Language :: Python :: 3
Classifier: Operating System :: OS Independent
Requires-Python: >=3.11.4
License-File: LICENSE.txt
Requires-Dist: datetime>=5.3
Requires-Dist: matplotlib>=3.8.2
Requires-Dist: numpy>=1.26.4
Requires-Dist: pandas>=2.2.0
Requires-Dist: pyodbc>=5.0.1
Requires-Dist: scipy>=1.11.4
Dynamic: license-file
